wmylxmj/__init__.py
wmylxmj/webspider/__init__.py
wmylxmj/webspider/bilibilispider.py
wmylxmj-0.0.4.dist-info/METADATA
wmylxmj-0.0.4.dist-info/RECORD
wmylxmj-0.0.4.dist-info/WHEEL
wmylxmj-0.0.4.dist-info/top_level.txt
