Metadata-Version: 2.1
Name: wmylxmj
Version: 0.0.4
Summary: bilibili spider
Home-page: https://github.com/wmylxmj/My-Python-Package
Author: wmy
Author-email: 1397322329@qq.com
License: UNKNOWN
Keywords: wmylxmj,webspider
Platform: UNKNOWN
Classifier: Programming Language :: Python :: 3
Classifier: License :: OSI Approved :: MIT License
Classifier: Operating System :: OS Independent
Requires-Dist: matplotlib
Requires-Dist: selenium
Requires-Dist: numpy
Requires-Dist: bs4
